tablebase/__init__.py
tablebase/tablebase.py
tablebase-1.7.0.dist-info/LICENSE
tablebase-1.7.0.dist-info/LICENSE.txt
tablebase-1.7.0.dist-info/METADATA
tablebase-1.7.0.dist-info/WHEEL
tablebase-1.7.0.dist-info/top_level.txt
tablebase-1.7.0.dist-info/RECORD
