Metadata-Version: 2.1
Name: tablebase
Version: 1.7.0
Summary: A lightweight tool to make tables easily in python.
Home-page: https://github.com/sasmlange/tablebase
Author: Maximilian Lange
Author-email: maxhlange@gmail.com
Classifier: License :: OSI Approved :: MIT License
Classifier: Programming Language :: Python :: 3
License-File: LICENSE
License-File: LICENSE.txt
